lumo_data/__init__.py
lumo_data/base.py
lumo_data/builder.py
lumo_data/dataloader.py
lumo_data/dataset.py
lumo_data/struct.py
lumo_data-0.1.1.dist-info/LICENSE
lumo_data-0.1.1.dist-info/METADATA
lumo_data-0.1.1.dist-info/WHEEL
lumo_data-0.1.1.dist-info/top_level.txt
lumo_data-0.1.1.dist-info/RECORD
